chemcluster/__init__.py
chemcluster/__main__.py
chemcluster/app.py
chemcluster/core.py
chemcluster/.streamlit/config.toml
chemcluster-0.1.42.dist-info/licenses/LICENSE
chemcluster-0.1.42.dist-info/METADATA
chemcluster-0.1.42.dist-info/WHEEL
chemcluster-0.1.42.dist-info/entry_points.txt
chemcluster-0.1.42.dist-info/top_level.txt
chemcluster-0.1.42.dist-info/RECORD
