Metadata-Version: 2.4
Name: chemcluster
Version: 0.1.42
Summary: Streamlit app to explore chemical clustering!
Author-email: Elisa Rubbia <elisa.rubbia@epfl.ch>, Romain Guichonnet <romain.guichonnet@epfl.ch>, Flavia Zabala Perez <flavia.zabalaperez@epfl.ch>
License: MIT License
Requires-Python: >=3.10
License-File: LICENSE
Requires-Dist: rdkit
Requires-Dist: streamlit==1.45.1
Requires-Dist: py3dmol
Requires-Dist: scikit-learn
Requires-Dist: plotly==5.19.0
Requires-Dist: streamlit-plotly-events==0.0.6
Requires-Dist: matplotlib
Provides-Extra: test
Requires-Dist: pytest; extra == "test"
Requires-Dist: tox; extra == "test"
Dynamic: license-file
